mixin/__init__.py
pvradar/__init__.py
pvradar/sdk/__init__.py
pvradar/sdk/sdk_facade.py
pvradar/sdk/client/Query.py
pvradar/sdk/client/SyncClient.py
pvradar/sdk/common/constants.py
pvradar/sdk/common/csv_utils.py
pvradar/sdk/common/dd_types.py
pvradar/sdk/common/exceptions.py
pvradar-0.0.3.dist-info/LICENSE
pvradar-0.0.3.dist-info/METADATA
pvradar-0.0.3.dist-info/WHEEL
pvradar-0.0.3.dist-info/top_level.txt
pvradar-0.0.3.dist-info/RECORD
